speechify/__init__.py
speechify/speechify.py
speechify-0.0.0.dist-info/METADATA
speechify-0.0.0.dist-info/WHEEL
speechify-0.0.0.dist-info/top_level.txt
speechify-0.0.0.dist-info/RECORD
