Metadata-Version: 2.1
Name: speechify
Version: 0.0.0
Summary: Unofficial speechify TTS module
Home-page: https://github.com/rewrite5/speechify-tools
Author: Billy Bat
Author-email: billybat@duck.com
Classifier: Development Status :: 3 - Alpha
Classifier: Intended Audience :: Developers
Classifier: Programming Language :: Python :: 3
Classifier: Programming Language :: Python :: 3.6
Classifier: Programming Language :: Python :: 3.7
Classifier: Topic :: Software Development
Classifier: License :: OSI Approved :: MIT License
Classifier: Operating System :: OS Independent
Requires-Python: ~=3.9
Requires-Dist: certifi ==2024.6.2
Requires-Dist: charset-normalizer ==3.3.2
Requires-Dist: idna ==3.7
Requires-Dist: requests ==2.32.3
Requires-Dist: tabulate ==0.9.0
Requires-Dist: urllib3 ==2.2.2
Provides-Extra: dev
Requires-Dist: setuptools ; extra == 'dev'
Requires-Dist: wheel ; extra == 'dev'
Requires-Dist: twine ; extra == 'dev'
Requires-Dist: Sphinx ; extra == 'dev'
